{
  "version": 1,
  "base": {
    "w": 1704,
    "h": 786
  },
  "selectedScale": 1.22,
  "selectedDy": -18,
  "cardFramePad": 0.14,
  "cards": {
    "act1": {
      "x": 55,
      "y": 230,
      "w": 245,
      "h": 375
    },
    "act2": {
      "x": 340,
      "y": 235,
      "w": 235,
      "h": 360
    },
    "act3": {
      "x": 580,
      "y": 235,
      "w": 235,
      "h": 360
    },
    "act4": {
      "x": 825,
      "y": 235,
      "w": 235,
      "h": 360
    },
    "act5": {
      "x": 1070,
      "y": 235,
      "w": 235,
      "h": 360
    }
  },
  "side": {
    "x": 1352,
    "y": 118,
    "w": 326,
    "h": 612
  },
  "ball": {
    "size": 132,
    "dy": 34
  }
}